{
  "test002": {
    "basic": {
      "checkIns": [
        {
          "date": "2026-07-07",
          "seconds": 0,
          "completed": false
        }
      ],
      "learned": [],
      "learnedDates": {},
      "mastered": [],
      "monthlyTests": [],
      "readIndex": 0,
      "speakScores": {},
      "spellIndex": 0,
      "totalSeconds": 0,
      "weeklyTests": []
    },
    "business": {
      "checkIns": [],
      "learned": [],
      "learnedDates": {},
      "mastered": [],
      "monthlyTests": [],
      "readIndex": 0,
      "speakScores": {},
      "spellIndex": 0,
      "totalSeconds": 0,
      "unlocked": false,
      "weeklyTests": []
    }
  },
  "058704": {
    "basic": {
      "readIndex": 0,
      "spellIndex": 0,
      "learned": [],
      "learnedDates": {},
      "mastered": [],
      "speakScores": {},
      "checkIns": [],
      "weeklyTests": [],
      "monthlyTests": [],
      "totalSeconds": 0
    },
    "business": {
      "readIndex": 0,
      "spellIndex": 0,
      "learned": [],
      "learnedDates": {},
      "mastered": [],
      "speakScores": {},
      "checkIns": [],
      "weeklyTests": [],
      "monthlyTests": [],
      "totalSeconds": 0,
      "unlocked": false
    }
  },
  "100031": {
    "basic": {
      "readIndex": 0,
      "spellIndex": 0,
      "learned": [],
      "learnedDates": {},
      "mastered": [],
      "speakScores": {},
      "checkIns": [],
      "weeklyTests": [],
      "monthlyTests": [],
      "totalSeconds": 0
    },
    "business": {
      "readIndex": 0,
      "spellIndex": 0,
      "learned": [],
      "learnedDates": {},
      "mastered": [],
      "speakScores": {},
      "checkIns": [],
      "weeklyTests": [],
      "monthlyTests": [],
      "totalSeconds": 0,
      "unlocked": false
    }
  },
  "147407": {
    "basic": {
      "checkIns": [
        {
          "completed": false,
          "date": "2026-07-06",
          "seconds": 6
        },
        {
          "completed": false,
          "date": "2026-07-07",
          "seconds": 355
        },
        {
          "completed": false,
          "date": "2026-07-08",
          "seconds": 7
        },
        {
          "completed": false,
          "date": "2026-07-09",
          "seconds": 153
        },
        {
          "completed": false,
          "date": "2026-07-10",
          "seconds": 12
        }
      ],
      "learned": [
        1,
        2,
        3,
        4,
        5,
        6
      ],
      "learnedDates": {
        "1": "2026-07-09",
        "2": "2026-07-09",
        "3": "2026-07-09",
        "4": "2026-07-07",
        "5": "2026-07-07",
        "6": "2026-07-09"
      },
      "mastered": [
        "1"
      ],
      "monthlyTests": [],
      "readIndex": 6,
      "speakScores": {
        "1": {
          "ex1": 89,
          "ex2": 83,
          "ex3": 85,
          "phrase": 85
        },
        "2": {
          "ex1": 85,
          "ex2": 84,
          "ex3": 53,
          "phrase": 29
        },
        "3": {
          "ex3": 30,
          "phrase": 28
        },
        "4": {
          "ex1": 83,
          "ex2": 61,
          "ex3": 60,
          "phrase": 85
        },
        "5": {
          "ex1": 85,
          "ex2": 16,
          "ex3": 18,
          "phrase": 28
        },
        "6": {
          "phrase": 15
        },
        "7": {
          "phrase": 35
        }
      },
      "spellIndex": 1,
      "totalSeconds": 0,
      "weeklyTests": []
    },
    "business": {
      "checkIns": [
        {
          "completed": false,
          "date": "2026-07-09",
          "seconds": 98
        },
        {
          "completed": false,
          "date": "2026-07-10",
          "seconds": 51
        }
      ],
      "learned": [
        1,
        2,
        3
      ],
      "learnedDates": {
        "1": "2026-07-09",
        "2": "2026-07-09",
        "3": "2026-07-09"
      },
      "mastered": [],
      "monthlyTests": [],
      "readIndex": 3,
      "speakScores": {
        "4": {
          "s0": 0
        }
      },
      "spellIndex": 0,
      "totalSeconds": 0,
      "unlocked": true,
      "weeklyTests": []
    },
    "checkIns": [
      {
        "completed": false,
        "date": "2026-07-06",
        "seconds": 6
      },
      {
        "completed": false,
        "date": "2026-07-07",
        "seconds": 355
      },
      {
        "completed": false,
        "date": "2026-07-08",
        "seconds": 7
      },
      {
        "completed": false,
        "date": "2026-07-09",
        "seconds": 153
      },
      {
        "completed": false,
        "date": "2026-07-10",
        "seconds": 130
      }
    ]
  },
  "407556": {
    "basic": {
      "checkIns": [
        {
          "completed": false,
          "date": "2026-07-07",
          "seconds": 15
        },
        {
          "completed": false,
          "date": "2026-07-08",
          "seconds": 179
        },
        {
          "date": "2026-07-09",
          "seconds": 59,
          "completed": false
        }
      ],
      "learned": [
        1,
        2,
        3,
        4,
        5,
        6,
        7,
        8,
        9,
        10,
        11
      ],
      "learnedDates": {
        "1": "2026-07-07",
        "2": "2026-07-07",
        "3": "2026-07-07",
        "4": "2026-07-07",
        "5": "2026-07-07",
        "6": "2026-07-07",
        "7": "2026-07-07",
        "8": "2026-07-07",
        "9": "2026-07-08",
        "10": "2026-07-09",
        "11": "2026-07-09"
      },
      "mastered": [
        "10",
        "11"
      ],
      "monthlyTests": [],
      "readIndex": 11,
      "speakScores": {
        "9": {
          "ex1": 84,
          "ex2": 62,
          "phrase": 85
        },
        "10": {
          "ex1": 85,
          "ex2": 87,
          "ex3": 83,
          "phrase": 85
        },
        "11": {
          "phrase": 85,
          "ex1": 86,
          "ex2": 85,
          "ex3": 88
        }
      },
      "spellIndex": 65,
      "totalSeconds": 0,
      "weeklyTests": []
    },
    "business": {
      "checkIns": [],
      "learned": [],
      "learnedDates": {},
      "mastered": [],
      "monthlyTests": [],
      "readIndex": 0,
      "speakScores": {},
      "spellIndex": 0,
      "totalSeconds": 0,
      "unlocked": false,
      "weeklyTests": []
    }
  },
  "102334": {
    "basic": {
      "readIndex": 0,
      "spellIndex": 0,
      "learned": [],
      "learnedDates": {},
      "mastered": [],
      "speakScores": {},
      "checkIns": [],
      "weeklyTests": [],
      "monthlyTests": [],
      "totalSeconds": 0
    },
    "business": {
      "readIndex": 0,
      "spellIndex": 0,
      "learned": [],
      "learnedDates": {},
      "mastered": [],
      "speakScores": {},
      "checkIns": [],
      "weeklyTests": [],
      "monthlyTests": [],
      "totalSeconds": 0,
      "unlocked": false
    }
  },
  "100256": {
    "basic": {
      "checkIns": [
        {
          "completed": false,
          "date": "2026-07-08",
          "seconds": 23
        },
        {
          "completed": false,
          "date": "2026-07-09",
          "seconds": 160
        }
      ],
      "learned": [
        1,
        2,
        3,
        4,
        5
      ],
      "learnedDates": {
        "1": "2026-07-10",
        "2": "2026-07-10",
        "3": "2026-07-10",
        "4": "2026-07-10",
        "5": "2026-07-10"
      },
      "mastered": [
        "1",
        "2"
      ],
      "monthlyTests": [],
      "readIndex": 5,
      "speakScores": {
        "1": {
          "ex1": 85,
          "ex2": 85,
          "ex3": 85,
          "phrase": 85
        },
        "2": {
          "ex1": 85,
          "ex2": 85,
          "ex3": 85,
          "phrase": 85
        },
        "3": {
          "ex1": 91,
          "ex2": 85,
          "ex3": 58,
          "phrase": 85
        },
        "4": {
          "ex1": 85,
          "ex3": 11,
          "phrase": 85,
          "ex2": 85
        },
        "5": {
          "phrase": 21
        }
      },
      "spellIndex": 0,
      "totalSeconds": 0,
      "weeklyTests": []
    },
    "business": {
      "checkIns": [],
      "learned": [
        1
      ],
      "learnedDates": {
        "1": "2026-07-10"
      },
      "mastered": [],
      "monthlyTests": [],
      "readIndex": 1,
      "speakScores": {},
      "spellIndex": 0,
      "totalSeconds": 0,
      "unlocked": true,
      "weeklyTests": []
    },
    "checkIns": [
      {
        "completed": false,
        "date": "2026-07-08",
        "seconds": 23
      },
      {
        "completed": false,
        "date": "2026-07-09",
        "seconds": 160
      },
      {
        "completed": false,
        "date": "2026-07-10",
        "seconds": 259
      }
    ]
  },
  "190763": {
    "basic": {
      "readIndex": 0,
      "spellIndex": 0,
      "learned": [],
      "learnedDates": {},
      "mastered": [],
      "speakScores": {},
      "checkIns": [],
      "weeklyTests": [],
      "monthlyTests": [],
      "totalSeconds": 0
    },
    "business": {
      "readIndex": 0,
      "spellIndex": 0,
      "learned": [],
      "learnedDates": {},
      "mastered": [],
      "speakScores": {},
      "checkIns": [],
      "weeklyTests": [],
      "monthlyTests": [],
      "totalSeconds": 0,
      "unlocked": false
    }
  },
  "233593": {
    "basic": {
      "checkIns": [
        {
          "completed": false,
          "date": "2026-07-09",
          "seconds": 326
        }
      ],
      "learned": [
        1,
        2,
        3,
        4,
        5
      ],
      "learnedDates": {
        "1": "2026-07-09",
        "2": "2026-07-09",
        "3": "2026-07-09",
        "4": "2026-07-09",
        "5": "2026-07-09"
      },
      "mastered": [
        "1",
        "2",
        "3",
        "4",
        "5"
      ],
      "monthlyTests": [],
      "readIndex": 5,
      "speakScores": {
        "1": {
          "ex1": 94,
          "ex2": 82,
          "ex3": 90,
          "phrase": 85
        },
        "2": {
          "ex1": 87,
          "ex2": 93,
          "ex3": 82,
          "phrase": 85
        },
        "3": {
          "ex1": 85,
          "ex2": 96,
          "ex3": 95,
          "phrase": 85
        },
        "4": {
          "ex1": 85,
          "ex2": 85,
          "ex3": 84,
          "phrase": 85
        },
        "5": {
          "ex1": 93,
          "ex2": 85,
          "ex3": 88,
          "phrase": 85
        },
        "6": {
          "phrase": 65
        }
      },
      "spellIndex": 0,
      "totalSeconds": 0,
      "weeklyTests": []
    },
    "business": {
      "checkIns": [],
      "learned": [],
      "learnedDates": {},
      "mastered": [],
      "monthlyTests": [],
      "readIndex": 0,
      "speakScores": {},
      "spellIndex": 0,
      "totalSeconds": 0,
      "unlocked": false,
      "weeklyTests": []
    }
  },
  "252250": {
    "basic": {
      "readIndex": 0,
      "spellIndex": 0,
      "learned": [],
      "learnedDates": {},
      "mastered": [],
      "speakScores": {},
      "checkIns": [],
      "weeklyTests": [],
      "monthlyTests": [],
      "totalSeconds": 0
    },
    "business": {
      "readIndex": 0,
      "spellIndex": 0,
      "learned": [],
      "learnedDates": {},
      "mastered": [],
      "speakScores": {},
      "checkIns": [],
      "weeklyTests": [],
      "monthlyTests": [],
      "totalSeconds": 0,
      "unlocked": false
    }
  },
  "253010": {
    "basic": {
      "readIndex": 0,
      "spellIndex": 0,
      "learned": [],
      "learnedDates": {},
      "mastered": [],
      "speakScores": {},
      "checkIns": [],
      "weeklyTests": [],
      "monthlyTests": [],
      "totalSeconds": 0
    },
    "business": {
      "readIndex": 0,
      "spellIndex": 0,
      "learned": [],
      "learnedDates": {},
      "mastered": [],
      "speakScores": {},
      "checkIns": [],
      "weeklyTests": [],
      "monthlyTests": [],
      "totalSeconds": 0,
      "unlocked": false
    }
  },
  "073508": {
    "basic": {
      "readIndex": 0,
      "spellIndex": 0,
      "learned": [],
      "learnedDates": {},
      "mastered": [],
      "speakScores": {},
      "checkIns": [],
      "weeklyTests": [],
      "monthlyTests": [],
      "totalSeconds": 0
    },
    "business": {
      "readIndex": 0,
      "spellIndex": 0,
      "learned": [],
      "learnedDates": {},
      "mastered": [],
      "speakScores": {},
      "checkIns": [],
      "weeklyTests": [],
      "monthlyTests": [],
      "totalSeconds": 0,
      "unlocked": false
    }
  },
  "238240": {
    "basic": {
      "readIndex": 0,
      "spellIndex": 0,
      "learned": [],
      "learnedDates": {},
      "mastered": [],
      "speakScores": {},
      "checkIns": [],
      "weeklyTests": [],
      "monthlyTests": [],
      "totalSeconds": 0
    },
    "business": {
      "readIndex": 0,
      "spellIndex": 0,
      "learned": [],
      "learnedDates": {},
      "mastered": [],
      "speakScores": {},
      "checkIns": [],
      "weeklyTests": [],
      "monthlyTests": [],
      "totalSeconds": 0,
      "unlocked": false
    }
  },
  "110233": {
    "basic": {
      "checkIns": [
        {
          "date": "2026-07-08",
          "seconds": 0,
          "completed": false
        }
      ],
      "learned": [],
      "learnedDates": {},
      "mastered": [],
      "monthlyTests": [],
      "readIndex": 0,
      "speakScores": {},
      "spellIndex": 0,
      "totalSeconds": 0,
      "weeklyTests": []
    },
    "business": {
      "checkIns": [],
      "learned": [],
      "learnedDates": {},
      "mastered": [],
      "monthlyTests": [],
      "readIndex": 0,
      "speakScores": {},
      "spellIndex": 0,
      "totalSeconds": 0,
      "unlocked": false,
      "weeklyTests": []
    }
  },
  "342114": {
    "basic": {
      "readIndex": 0,
      "spellIndex": 0,
      "learned": [],
      "learnedDates": {},
      "mastered": [],
      "speakScores": {},
      "checkIns": [],
      "weeklyTests": [],
      "monthlyTests": [],
      "totalSeconds": 0
    },
    "business": {
      "readIndex": 0,
      "spellIndex": 0,
      "learned": [],
      "learnedDates": {},
      "mastered": [],
      "speakScores": {},
      "checkIns": [],
      "weeklyTests": [],
      "monthlyTests": [],
      "totalSeconds": 0,
      "unlocked": false
    }
  },
  "339911": {
    "basic": {
      "checkIns": [
        {
          "date": "2026-07-08",
          "seconds": 229,
          "completed": false
        }
      ],
      "learned": [
        1,
        2,
        3,
        4,
        5
      ],
      "learnedDates": {
        "1": "2026-07-08",
        "2": "2026-07-08",
        "3": "2026-07-08",
        "4": "2026-07-08",
        "5": "2026-07-08"
      },
      "mastered": [],
      "monthlyTests": [],
      "readIndex": 5,
      "speakScores": {},
      "spellIndex": 0,
      "totalSeconds": 0,
      "weeklyTests": []
    },
    "business": {
      "checkIns": [],
      "learned": [],
      "learnedDates": {},
      "mastered": [],
      "monthlyTests": [],
      "readIndex": 0,
      "speakScores": {},
      "spellIndex": 0,
      "totalSeconds": 0,
      "unlocked": false,
      "weeklyTests": []
    }
  },
  "059707": {
    "basic": {
      "readIndex": 0,
      "spellIndex": 0,
      "learned": [],
      "learnedDates": {},
      "mastered": [],
      "speakScores": {},
      "checkIns": [],
      "weeklyTests": [],
      "monthlyTests": [],
      "totalSeconds": 0
    },
    "business": {
      "readIndex": 0,
      "spellIndex": 0,
      "learned": [],
      "learnedDates": {},
      "mastered": [],
      "speakScores": {},
      "checkIns": [],
      "weeklyTests": [],
      "monthlyTests": [],
      "totalSeconds": 0,
      "unlocked": false
    }
  },
  "189146": {
    "basic": {
      "checkIns": [
        {
          "completed": false,
          "date": "2026-07-09",
          "seconds": 429
        }
      ],
      "learned": [
        1,
        2,
        3,
        4,
        5,
        6
      ],
      "learnedDates": {
        "1": "2026-07-09",
        "2": "2026-07-09",
        "3": "2026-07-09",
        "4": "2026-07-09",
        "5": "2026-07-09",
        "6": "2026-07-09"
      },
      "mastered": [
        "2",
        "1",
        "3",
        "4",
        "5",
        "6"
      ],
      "monthlyTests": [],
      "readIndex": 6,
      "speakScores": {
        "1": {
          "ex1": 94,
          "ex2": 85,
          "ex3": 85,
          "phrase": 85
        },
        "2": {
          "ex1": 96,
          "ex2": 85,
          "ex3": 81,
          "phrase": 85
        },
        "3": {
          "ex1": 85,
          "ex2": 83,
          "ex3": 92,
          "phrase": 85
        },
        "4": {
          "ex1": 85,
          "ex2": 93,
          "ex3": 86,
          "phrase": 85
        },
        "5": {
          "phrase": 81,
          "ex1": 93,
          "ex2": 85,
          "ex3": 96
        },
        "6": {
          "phrase": 85,
          "ex1": 93,
          "ex2": 87,
          "ex3": 85
        }
      },
      "spellIndex": 49,
      "totalSeconds": 0,
      "weeklyTests": []
    },
    "business": {
      "checkIns": [],
      "learned": [],
      "learnedDates": {},
      "mastered": [],
      "monthlyTests": [],
      "readIndex": 0,
      "speakScores": {},
      "spellIndex": 0,
      "totalSeconds": 0,
      "unlocked": false,
      "weeklyTests": []
    }
  },
  "228174": {
    "basic": {
      "readIndex": 0,
      "spellIndex": 0,
      "learned": [],
      "learnedDates": {},
      "mastered": [],
      "speakScores": {},
      "checkIns": [],
      "weeklyTests": [],
      "monthlyTests": [],
      "totalSeconds": 0
    },
    "business": {
      "readIndex": 0,
      "spellIndex": 0,
      "learned": [],
      "learnedDates": {},
      "mastered": [],
      "speakScores": {},
      "checkIns": [],
      "weeklyTests": [],
      "monthlyTests": [],
      "totalSeconds": 0,
      "unlocked": false
    }
  }
}